docs/source/conf.py
docs/source/index.rst
docs/source/moreinfo.rst
docs/source/poly.py
docs/source/screenshots.rst
docs/source/_static/custom.css
docs/source/admin/configuration.rst
docs/source/admin/design.rst
docs/source/admin/index.rst
docs/source/admin/kickstart.rst
docs/source/admin/putget.rst
docs/source/admin/spark.rst
docs/source/admin/windows.rst
docs/source/changes/index.rst
docs/source/changes/v0.15.3.rst
docs/source/changes/v0.15.5.rst
docs/source/changes/v0.16.0.rst
docs/source/changes/v0.16.1.rst
docs/source/changes/v0.16.2.rst
docs/source/changes/v0.16.3.rst
docs/source/changes/v0.4.rst
docs/source/changes/v0.5.rst
docs/source/changes/v0.6.rst
docs/source/changes/v0.7.rst
docs/source/changes/v0.8.5.rst
docs/source/changes/v0.8.rst
docs/source/changes/v0.9.rst
docs/source/devguide/architecture.rst
docs/source/devguide/custom.rst
docs/source/devguide/index.rst
docs/source/devguide/metadata.rst
docs/source/devguide/mixins.rst
docs/source/devguide/storage.rst
docs/source/guide/index.rst
docs/source/guide/advanced/index.rst
docs/source/guide/advanced/customizing/custombackends.rst
docs/source/guide/advanced/customizing/index.rst
docs/source/guide/advanced/integration/buckets.rst
docs/source/guide/advanced/integration/index.rst
docs/source/guide/advanced/integration/runtimes.rst
docs/source/guide/cli/cloud.rst
docs/source/guide/cli/datasets.rst
docs/source/guide/cli/index.rst
docs/source/guide/cli/intro.rst
docs/source/guide/cli/jobs.rst
docs/source/guide/cli/models.rst
docs/source/guide/cli/runtime.rst
docs/source/guide/cli/scripts.rst
docs/source/guide/clusters/index.rst
docs/source/guide/clusters/intro.rst
docs/source/guide/clusters/logging.rst
docs/source/guide/clusters/mlops.rst
docs/source/guide/clusters/monitoring.rst
docs/source/guide/clusters/restapi.rst
docs/source/guide/clusters/runtimes.rst
docs/source/guide/datasets/files.rst
docs/source/guide/datasets/filterdf.rst
docs/source/guide/datasets/index.rst
omegaml-0.16.4.dist-info/LICENSE
omegaml-0.16.4.dist-info/LICENSE-NOSELLCLAUSE
omegaml-0.16.4.dist-info/LICENSES-THIRDPARTY
omegaml-0.16.4.dist-info/METADATA
omegaml-0.16.4.dist-info/NOTICE
omegaml-0.16.4.dist-info/WHEEL
omegaml-0.16.4.dist-info/entry_points.txt
omegaml-0.16.4.dist-info/top_level.txt
omegaml-0.16.4.dist-info/RECORD
