Metadata-Version: 2.2
Name: omegaml
Version: 0.16.4
Summary: An open source DataOps, MLOps platform for humans
Home-page: https://omegaml.io/
Author: Patrick Senti
Author-email: patrick.senti@omegaml.io
License: Apache 2.0 + "No Sell, Consulting Yes" License Condition
Project-URL: Documentation, https://omegaml.github.io/omegaml/
Project-URL: Issues, https://github.com/omegaml/omegaml/issues
Project-URL: Source, https://github.com/omegaml/omegaml
Classifier: License :: OSI Approved :: Apache Software License
Classifier: Programming Language :: Python
Classifier: Programming Language :: Python :: 3
Classifier: Programming Language :: Python :: 3.10
Classifier: Programming Language :: Python :: 3.11
Classifier: Programming Language :: Python :: 3.12
Classifier: Programming Language :: Python :: Implementation :: CPython
Classifier: Development Status :: 4 - Beta
Classifier: Topic :: Scientific/Engineering :: Artificial Intelligence
Classifier: Topic :: Software Development
Classifier: Operating System :: POSIX :: Linux
Classifier: License :: OSI Approved :: Apache Software License
License-File: LICENSE
License-File: LICENSE-NOSELLCLAUSE
License-File: LICENSES-THIRDPARTY
License-File: NOTICE
Requires-Dist: celery<6.0,>5
Requires-Dist: joblib>=0.9.4
Requires-Dist: jupyter-client>=4.1.1
Requires-Dist: ipython>=8.0
Requires-Dist: mongoengine>=0.29
Requires-Dist: pandas<2.2,>=2.0.0
Requires-Dist: numpy>=1.16.4
Requires-Dist: scipy>=0.17.0
Requires-Dist: scikit-learn>=1.2
Requires-Dist: PyYAML>=3.12
Requires-Dist: flask-restx>=1.1.0
Requires-Dist: Flask>3.0
Requires-Dist: Flask-Session
Requires-Dist: croniter>=0.3.30
Requires-Dist: nbformat>=4.0.1
Requires-Dist: nbconvert>=6.4.0
Requires-Dist: dill>0.3.6
Requires-Dist: callable-pip>=1.0.0
Requires-Dist: appdirs>=1.4.3
Requires-Dist: cron-descriptor>=1.2.31
Requires-Dist: docopt>=0.6.2
Requires-Dist: requests>=2.20.0
Requires-Dist: tqdm>=4.32.2
Requires-Dist: yaspin
Requires-Dist: honcho>=1.0.1
Requires-Dist: tabulate>=0.8.2
Requires-Dist: smart_open
Requires-Dist: imageio>=2.3.0
Requires-Dist: psutil>=5.8
Requires-Dist: cachetools>=5.0.0
Requires-Dist: apispec>=5.2.2
Requires-Dist: marshmallow>=3.17.0
Requires-Dist: sqlalchemy<2
Requires-Dist: minibatch[omegaml]
Requires-Dist: validators
Requires-Dist: dnspython>=2.6.1
Requires-Dist: idna>=3.7
Requires-Dist: pymongo>=4.10
Provides-Extra: all
Requires-Dist: tables>=3.7; extra == "all"
Requires-Dist: matplotlib>=3.5; extra == "all"
Requires-Dist: seaborn>=0.11; extra == "all"
Requires-Dist: dash>=2.9; extra == "all"
Requires-Dist: plotly; extra == "all"
Requires-Dist: jupyterlab; extra == "all"
Requires-Dist: jupyterhub; extra == "all"
Requires-Dist: notebook; extra == "all"
Requires-Dist: nbclassic; extra == "all"
Requires-Dist: mlflow-skinny>=1.2; extra == "all"
Requires-Dist: tensorflow<2.16,>2; extra == "all"
Requires-Dist: json5>0.9; extra == "all"
Requires-Dist: google_auth_oauthlib>=1; extra == "all"
Requires-Dist: filelock>=3.0.0; extra == "all"
Requires-Dist: gitdb>4.0; extra == "all"
Requires-Dist: debugpy>=1.7; extra == "all"
Requires-Dist: cryptography>=41.0; extra == "all"
Requires-Dist: Babel>2.13; extra == "all"
Requires-Dist: attrs>=21.4.0; extra == "all"
Requires-Dist: asttokens>=2.4; extra == "all"
Requires-Dist: anyio>=3.7; extra == "all"
Requires-Dist: tomli>=2.0.0; extra == "all"
Provides-Extra: client
Requires-Dist: tables>=3.7; extra == "client"
Requires-Dist: dash>=2.9; extra == "client"
Requires-Dist: plotly; extra == "client"
Provides-Extra: dev
Requires-Dist: pytest; extra == "dev"
Requires-Dist: twine; extra == "dev"
Requires-Dist: flake8; extra == "dev"
Requires-Dist: mock; extra == "dev"
Requires-Dist: behave; extra == "dev"
Requires-Dist: splinter[selenium]; extra == "dev"
Requires-Dist: ipdb; extra == "dev"
Requires-Dist: bumpversion; extra == "dev"
Requires-Dist: pip-tools; extra == "dev"
Dynamic: author
Dynamic: author-email
Dynamic: classifier
Dynamic: description
Dynamic: description-content-type
Dynamic: home-page
Dynamic: license
Dynamic: project-url
Dynamic: provides-extra
Dynamic: requires-dist
